MANIFEST.in
README.md
setup.py
dockx_checker.egg-info/PKG-INFO
dockx_checker.egg-info/SOURCES.txt
dockx_checker.egg-info/dependency_links.txt
dockx_checker.egg-info/entry_points.txt
dockx_checker.egg-info/not-zip-safe
dockx_checker.egg-info/requires.txt
dockx_checker.egg-info/top_level.txt
dockx_checker_src/__init__.py
dockx_checker_src/cmd.py
dockx_checker_src/service.py
dockx_checker_src/static/index.css
dockx_checker_src/static/css/bootstrap-grid.css
dockx_checker_src/static/css/bootstrap-grid.css.map
dockx_checker_src/static/css/bootstrap-grid.min.css
dockx_checker_src/static/css/bootstrap-grid.min.css.map
dockx_checker_src/static/css/bootstrap-grid.rtl.css
dockx_checker_src/static/css/bootstrap-grid.rtl.css.map
dockx_checker_src/static/css/bootstrap-grid.rtl.min.css
dockx_checker_src/static/css/bootstrap-grid.rtl.min.css.map
dockx_checker_src/static/css/bootstrap-reboot.css
dockx_checker_src/static/css/bootstrap-reboot.css.map
dockx_checker_src/static/css/bootstrap-reboot.min.css
dockx_checker_src/static/css/bootstrap-reboot.min.css.map
dockx_checker_src/static/css/bootstrap-reboot.rtl.css
dockx_checker_src/static/css/bootstrap-reboot.rtl.css.map
dockx_checker_src/static/css/bootstrap-reboot.rtl.min.css
dockx_checker_src/static/css/bootstrap-reboot.rtl.min.css.map
dockx_checker_src/static/css/bootstrap-utilities.css
dockx_checker_src/static/css/bootstrap-utilities.css.map
dockx_checker_src/static/css/bootstrap-utilities.min.css
dockx_checker_src/static/css/bootstrap-utilities.min.css.map
dockx_checker_src/static/css/bootstrap-utilities.rtl.css
dockx_checker_src/static/css/bootstrap-utilities.rtl.css.map
dockx_checker_src/static/css/bootstrap-utilities.rtl.min.css
dockx_checker_src/static/css/bootstrap-utilities.rtl.min.css.map
dockx_checker_src/static/css/bootstrap.css
dockx_checker_src/static/css/bootstrap.css.map
dockx_checker_src/static/css/bootstrap.min.css
dockx_checker_src/static/css/bootstrap.min.css.map
dockx_checker_src/static/css/bootstrap.rtl.css
dockx_checker_src/static/css/bootstrap.rtl.css.map
dockx_checker_src/static/css/bootstrap.rtl.min.css
dockx_checker_src/static/css/bootstrap.rtl.min.css.map
dockx_checker_src/static/downloads/test.txt
dockx_checker_src/static/js/bootstrap.bundle.js
