Metadata-Version: 2.1
Name: dockx-checker
Version: 0.0.1
Summary: a check tools
Home-page: https://github.com/xxx
Author: auth
Author-email: xxx@gmail.com
License: MIT
Platform: UNKNOWN
